[
    {
        "type": "function",
        "name": "SUPPORTS_INTERFACE_STORAGE_POSITION",
        "inputs": [],
        "outputs": [
            {
                "name": "",
                "type": "bytes32",
                "internalType": "bytes32"
            }
        ],
        "stateMutability": "view",
        "selector": "0x3a53ff49"
    },
    {
        "type": "function",
        "name": "accounts",
        "inputs": [],
        "outputs": [
            {
                "name": "",
                "type": "address[]",
                "internalType": "address[]"
            }
        ],
        "stateMutability": "view",
        "selector": "0x68cd03f6"
    },
    {
        "type": "function",
        "name": "ban",
        "inputs": [
            {
                "name": "account",
                "type": "address",
                "internalType": "address"
            }
        ],
        "outputs": [],
        "stateMutability": "nonpayable",
        "selector": "0x97c3ccd8"
    },
    {
        "type": "function",
        "name": "chainId",
        "inputs": [],
        "outputs": [
            {
                "name": "",
                "type": "uint256",
                "internalType": "uint256"
            }
        ],
        "stateMutability": "view",
        "selector": "0x9a8a0592"
    },
    {
        "type": "function",
        "name": "disableGlobalDebugging",
        "inputs": [],
        "outputs": [],
        "stateMutability": "nonpayable",
        "selector": "0x8374643d"
    },
    {
        "type": "function",
        "name": "enableGlobalDebugging",
        "inputs": [],
        "outputs": [],
        "stateMutability": "nonpayable",
        "selector": "0xe30bbbd5"
    },
    {
        "type": "function",
        "name": "enforceAdmin",
        "inputs": [
            {
                "name": "account",
                "type": "address",
                "internalType": "address"
            }
        ],
        "outputs": [],
        "stateMutability": "view",
        "selector": "0x02f4ee72"
    },
    {
        "type": "function",
        "name": "enforceDebugger",
        "inputs": [
            {
                "name": "account",
                "type": "address",
                "internalType": "address"
            }
        ],
        "outputs": [],
        "stateMutability": "view",
        "selector": "0x57948da5"
    },
    {
        "type": "function",
        "name": "enforceGlobalDebuggingEnabled",
        "inputs": [],
        "outputs": [],
        "stateMutability": "view",
        "selector": "0x2e8a9a1f"
    },
    {
        "type": "function",
        "name": "enforceNotBanned",
        "inputs": [
            {
                "name": "account",
                "type": "address",
                "internalType": "address"
            }
        ],
        "outputs": [],
        "stateMutability": "view",
        "selector": "0x58036eae"
    },
    {
        "type": "function",
        "name": "enforceTestnet",
        "inputs": [],
        "outputs": [],
        "stateMutability": "view",
        "selector": "0x915d39e7"
    },
    {
        "type": "function",
        "name": "existsInSystem",
        "inputs": [
            {
                "name": "account",
                "type": "address",
                "internalType": "address"
            }
        ],
        "outputs": [
            {
                "name": "",
                "type": "bool",
                "internalType": "bool"
            }
        ],
        "stateMutability": "view",
        "selector": "0xb5e658a9"
    },
    {
        "type": "function",
        "name": "globalDebuggingEnabled",
        "inputs": [],
        "outputs": [
            {
                "name": "enabled",
                "type": "bool",
                "internalType": "bool"
            }
        ],
        "stateMutability": "view",
        "selector": "0xc5863a05"
    },
    {
        "type": "function",
        "name": "isAdmin",
        "inputs": [
            {
                "name": "account",
                "type": "address",
                "internalType": "address"
            }
        ],
        "outputs": [
            {
                "name": "",
                "type": "bool",
                "internalType": "bool"
            }
        ],
        "stateMutability": "view",
        "selector": "0x24d7806c"
    },
    {
        "type": "function",
        "name": "isBanned",
        "inputs": [
            {
                "name": "account",
                "type": "address",
                "internalType": "address"
            }
        ],
        "outputs": [
            {
                "name": "",
                "type": "bool",
                "internalType": "bool"
            }
        ],
        "stateMutability": "view",
        "selector": "0x97f735d5"
    },
    {
        "type": "function",
        "name": "isDebugger",
        "inputs": [
            {
                "name": "account",
                "type": "address",
                "internalType": "address"
            }
        ],
        "outputs": [
            {
                "name": "",
                "type": "bool",
                "internalType": "bool"
            }
        ],
        "stateMutability": "view",
        "selector": "0x9df37ebb"
    },
    {
        "type": "function",
        "name": "isMainnet",
        "inputs": [],
        "outputs": [
            {
                "name": "",
                "type": "bool",
                "internalType": "bool"
            }
        ],
        "stateMutability": "view",
        "selector": "0x42faac05"
    },
    {
        "type": "function",
        "name": "isTestnet",
        "inputs": [],
        "outputs": [
            {
                "name": "",
                "type": "bool",
                "internalType": "bool"
            }
        ],
        "stateMutability": "view",
        "selector": "0x92108c86"
    },
    {
        "type": "function",
        "name": "liftBan",
        "inputs": [
            {
                "name": "account",
                "type": "address",
                "internalType": "address"
            }
        ],
        "outputs": [],
        "stateMutability": "nonpayable",
        "selector": "0xf6a220b8"
    },
    {
        "type": "function",
        "name": "registerAdmin",
        "inputs": [
            {
                "name": "account",
                "type": "address",
                "internalType": "address"
            }
        ],
        "outputs": [],
        "stateMutability": "nonpayable",
        "selector": "0xc38c5813"
    },
    {
        "type": "function",
        "name": "registerDebugger",
        "inputs": [
            {
                "name": "account",
                "type": "address",
                "internalType": "address"
            }
        ],
        "outputs": [],
        "stateMutability": "nonpayable",
        "selector": "0xe5757adc"
    },
    {
        "type": "function",
        "name": "removePermissions",
        "inputs": [
            {
                "name": "account",
                "type": "address",
                "internalType": "address"
            }
        ],
        "outputs": [],
        "stateMutability": "nonpayable",
        "selector": "0x096f9460"
    },
    {
        "type": "function",
        "name": "role",
        "inputs": [
            {
                "name": "account",
                "type": "address",
                "internalType": "address"
            }
        ],
        "outputs": [
            {
                "name": "",
                "type": "tuple",
                "internalType": "struct ITestnetDebugRegistry.Role",
                "components": [
                    {
                        "name": "existsInSystem",
                        "type": "bool",
                        "internalType": "bool"
                    },
                    {
                        "name": "admin",
                        "type": "bool",
                        "internalType": "bool"
                    },
                    {
                        "name": "debugger",
                        "type": "bool",
                        "internalType": "bool"
                    },
                    {
                        "name": "banned",
                        "type": "bool",
                        "internalType": "bool"
                    }
                ]
            }
        ],
        "stateMutability": "view",
        "selector": "0xd590f8c9"
    },
    {
        "type": "event",
        "name": "AdminChanged",
        "inputs": [
            {
                "name": "previousAdmin",
                "type": "address",
                "indexed": false,
                "internalType": "address"
            },
            {
                "name": "newAdmin",
                "type": "address",
                "indexed": false,
                "internalType": "address"
            }
        ],
        "anonymous": false,
        "selector": "0x7e644d79"
    },
    {
        "type": "event",
        "name": "OwnershipTransferred",
        "inputs": [
            {
                "name": "previousOwner",
                "type": "address",
                "indexed": true,
                "internalType": "address"
            },
            {
                "name": "newOwner",
                "type": "address",
                "indexed": true,
                "internalType": "address"
            }
        ],
        "anonymous": false,
        "selector": "0x8be0079c"
    }
]